{
    "items": [
        "alexscaves:hood_of_darkness"
    ],
    "attributes": [
        {
            "id": "irons_spellbooks:blood_spell_power",
            "value": 0.2,
            "operation": "multiply_base",
            "slot": "head",
            "uuid": "1a4331a0-6eb4-14bf-a33a-125356f34a4c",
            "replace": true
        },
        {
            "id": "irons_spellbooks:eldritch_spell_power",
            "value": 0.1,
            "operation": "multiply_base",
            "slot": "head",
            "uuid": "ca22c8f2-6e45-145a-a12d-222346e35b59",
            "replace": true
        }
    ]
}