{
    "pools": [{
        "name": "map_pool",
        "rolls": 1,
        "entries": [
            {
                "type": "minecraft:item",
                "functions": [
                    {
                        "function": "minecraft:exploration_map",
                        "destination": "lootintegrations:nether_boss",
                        "zoom": 2,
                        "decoration": "target_x",
                        "skip_existing_chunks": true
                    },
                    { 
                        "function": "minecraft:set_name", 
                        "name": {
                            "translate": "Charred Map", 
                            "underlined": true 
                        } 
                    } 
                ],
                "name": "minecraft:map",
                "weight": 10
            },
            {
                "type": "empty",
                "weight": 90
            }
        ]
    }]
}